pytere/__init__.py
pytere-0.7.0.dist-info/LICENSE
pytere-0.7.0.dist-info/METADATA
pytere-0.7.0.dist-info/WHEEL
pytere-0.7.0.dist-info/top_level.txt
pytere-0.7.0.dist-info/RECORD
