Metadata-Version: 2.1
Name: pytere
Version: 0.7.0
Summary: A Python Template Repository
Home-page: https://github.com/astariul/pytere
Author: Nicolas REMOND
Author-email: remondnicola@gmail.com
License: UNKNOWN
Platform: UNKNOWN
Classifier: Programming Language :: Python :: 3.8
Classifier: Operating System :: OS Independent
Requires-Python: >=3.8
Provides-Extra: all
Requires-Dist: pytest ~=8.0 ; extra == 'all'
Requires-Dist: pytest-cov ~=4.1 ; extra == 'all'
Requires-Dist: pre-commit ~=3.0 ; extra == 'all'
Requires-Dist: ruff ~=0.2 ; extra == 'all'
Requires-Dist: mkdocs-material ~=9.0 ; extra == 'all'
Requires-Dist: mkdocstrings[python] ~=0.24 ; extra == 'all'
Requires-Dist: mike ~=2.0 ; extra == 'all'
Provides-Extra: dev
Requires-Dist: pytest ~=8.0 ; extra == 'dev'
Requires-Dist: pytest-cov ~=4.1 ; extra == 'dev'
Requires-Dist: pre-commit ~=3.0 ; extra == 'dev'
Requires-Dist: ruff ~=0.2 ; extra == 'dev'
Requires-Dist: mkdocs-material ~=9.0 ; extra == 'dev'
Requires-Dist: mkdocstrings[python] ~=0.24 ; extra == 'dev'
Requires-Dist: mike ~=2.0 ; extra == 'dev'
Provides-Extra: docs
Requires-Dist: mkdocs-material ~=9.0 ; extra == 'docs'
Requires-Dist: mkdocstrings[python] ~=0.24 ; extra == 'docs'
Requires-Dist: mike ~=2.0 ; extra == 'docs'
Provides-Extra: hook
Requires-Dist: pre-commit ~=3.0 ; extra == 'hook'
Provides-Extra: lint
Requires-Dist: ruff ~=0.2 ; extra == 'lint'
Provides-Extra: test
Requires-Dist: pytest ~=8.0 ; extra == 'test'
Requires-Dist: pytest-cov ~=4.1 ; extra == 'test'
